{"conversation_id": "1248458973524545538", "possibly_sensitive": false, "public_metrics": {"retweet_count": 0, "reply_count": 1, "like_count": 0, "quote_count": 0}, "text": "...to spread nTERROR about a virus yo created but let people think it is from our Lord The God.\n\nLet me repeat again. OUR LORD THE GOD ALLAH does  not send  diseases tto prevent HEALTHY INDIVIDUALS from accomplishing their religious duty; UPHOLD THE SABBATH", "created_at": "2020-04-10T04:29:24.000Z", "id": "1248468095653445634", "referenced_tweets": [{"type": "replied_to", "id": "1248468093573062656"}], "reply_settings": "everyone", "lang": "en", "entities": {"annotations": [{"start": 91, "end": 93, "probability": 0.7484, "type": "Other", "normalized_text": "God"}, {"start": 131, "end": 133, "probability": 0.7609, "type": "Other", "normalized_text": "GOD"}, {"start": 135, "end": 139, "probability": 0.858, "type": "Other", "normalized_text": "ALLAH"}]}, "author_id": "335858588", "in_reply_to_user_id": "335858588", "source": "Twitter for iPad"}