{"public_metrics": {"retweet_count": 0, "reply_count": 0, "like_count": 1, "quote_count": 0}, "conversation_id": "1250066794066444290", "created_at": "2020-04-14T16:39:49.000Z", "lang": "en", "reply_settings": "everyone", "referenced_tweets": [{"type": "replied_to", "id": "1250066794066444290"}], "entities": {"mentions": [{"start": 0, "end": 15, "username": "citizentvkenya", "id": "70394965"}], "annotations": [{"start": 50, "end": 59, "probability": 0.2989, "type": "Other", "normalized_text": "Vitamin C"}]}, "source": "Twitter for Android", "possibly_sensitive": false, "id": "1250101465223331842", "text": "@citizentvkenya And it even depletes your body of Vitamin  C,  which is required  to boost the immunity", "author_id": "2510470804", "in_reply_to_user_id": "70394965"}