{"geo": {"place_id": "827e412aeb7e3e98", "coordinates": {"type": "Point", "coordinates": [-1.52294578, 52.40750796]}}, "source": "Twitter for iPhone", "in_reply_to_user_id": "311516431", "reply_settings": "everyone", "conversation_id": "407248574099894272", "created_at": "2013-12-02T00:20:22.000Z", "referenced_tweets": [{"type": "replied_to", "id": "407302772150009857"}], "id": "407303190867353600", "author_id": "295310170", "lang": "en", "possibly_sensitive": false, "text": "@LolaMos__ I never said the movie would be scrapped", "public_metrics": {"retweet_count": 0, "reply_count": 1, "like_count": 0, "quote_count": 0}}