{"possibly_sensitive": false, "in_reply_to_user_id": "14940354", "referenced_tweets": [{"type": "replied_to", "id": "489872500462190593"}], "geo": {"place_id": "9d8ae4b0fac2036a", "coordinates": {"type": "Point", "coordinates": [-79.5266231, 8.9969264]}}, "reply_settings": "everyone", "id": "489898351886737408", "created_at": "2014-07-17T22:24:03.000Z", "public_metrics": {"retweet_count": 0, "reply_count": 0, "like_count": 0, "quote_count": 0}, "author_id": "217638725", "source": "Twitter for Android", "text": "@nycjim It not seems as a reliable source. Now all are fabricating they own versions.", "lang": "en", "conversation_id": "489872500462190593", "entities": {"mentions": [{"start": 0, "end": 7, "username": "nycjim", "id": "14940354"}]}}