{"conversation_id": "514142113601437696", "author_id": "2824820934", "source": "Twitter for Android", "possibly_sensitive": false, "created_at": "2014-09-23T05:02:50.000Z", "referenced_tweets": [{"type": "replied_to", "id": "514142113601437696"}], "text": "@CNN", "id": "514278696723550208", "lang": "und", "reply_settings": "everyone", "entities": {"mentions": [{"start": 0, "end": 4, "username": "CNN", "id": "759251"}]}, "public_metrics": {"retweet_count": 0, "reply_count": 0, "like_count": 0, "quote_count": 0}, "in_reply_to_user_id": "759251"}