{"entities": {"annotations": [{"start": 51, "end": 55, "probability": 0.4637, "type": "Other", "normalized_text": "Ebola"}], "mentions": [{"start": 0, "end": 6, "username": "MSNBC", "id": "2836421"}]}, "possibly_sensitive": false, "in_reply_to_user_id": "2836421", "public_metrics": {"retweet_count": 0, "reply_count": 0, "like_count": 0, "quote_count": 0}, "author_id": "799633632", "referenced_tweets": [{"type": "replied_to", "id": "521821037726797824"}], "created_at": "2014-10-14T11:21:31.000Z", "conversation_id": "521821037726797824", "id": "521984137851588608", "source": "TweetCaster for Android", "lang": "en", "reply_settings": "everyone", "text": "@msnbc how is these people are being infected with Ebola why are these people allowed to travel"}