{"geo": {"coordinates": {"type": "Point", "coordinates": [-117.1261761, 32.7688125]}, "place_id": "a592bd6ceb1319f7"}, "created_at": "2014-12-13T02:50:02.000Z", "source": "Twitter for Android", "public_metrics": {"retweet_count": 0, "reply_count": 0, "like_count": 0, "quote_count": 0}, "possibly_sensitive": false, "id": "543598693669421057", "text": "@NBCNews good news for me!!", "conversation_id": "543586319168196608", "entities": {"mentions": [{"start": 0, "end": 8, "username": "NBCNews", "id": "14173315"}]}, "lang": "en", "author_id": "1696677896", "referenced_tweets": [{"type": "replied_to", "id": "543586319168196608"}], "in_reply_to_user_id": "14173315", "reply_settings": "everyone"}