{"author_id": "2804531655", "public_metrics": {"retweet_count": 0, "reply_count": 0, "like_count": 0, "quote_count": 0}, "in_reply_to_user_id": "7587032", "text": "@SkyNews bollox!", "possibly_sensitive": false, "referenced_tweets": [{"type": "replied_to", "id": "544283772569788416"}], "source": "Twitter Web Client", "conversation_id": "544283772569788416", "created_at": "2014-12-15T00:23:30.000Z", "entities": {"mentions": [{"start": 0, "end": 8, "username": "SkyNews", "id": "7587032"}]}, "reply_settings": "everyone", "lang": "en", "id": "544286591515373569"}