{"lang": "en", "possibly_sensitive": false, "entities": {"urls": [{"start": 111, "end": 133, "url": "http://t.co/nXHAvOv6h1", "expanded_url": "http://thefederalist.com/2015/01/21/im-a-stay-at-home-working-mom-and-im-sick-of-being-insulted-by-the-president/", "display_url": "thefederalist.com/2015/01/21/im-\u2026"}], "hashtags": [{"start": 134, "end": 139, "tag": "SOTU"}], "mentions": [{"start": 11, "end": 23, "username": "JoyPullmann", "id": "736840885"}]}, "source": "Twitter for iPhone", "referenced_tweets": [{"type": "replied_to", "id": "557885928417816576"}], "author_id": "627830911", "in_reply_to_user_id": "736840885", "public_metrics": {"retweet_count": 0, "reply_count": 0, "like_count": 0, "quote_count": 0}, "conversation_id": "557885928417816576", "reply_settings": "everyone", "text": "Well said \"@JoyPullmann: Mr. President, stop mansplaining your \"need\" 2 have government care for *my* children http://t.co/nXHAvOv6h1 #SOTU\u201d", "created_at": "2015-01-21T13:59:46.000Z", "id": "557900361256935426"}