{"conversation_id": "614618682543616000", "possibly_sensitive": false, "public_metrics": {"retweet_count": 0, "reply_count": 0, "like_count": 0, "quote_count": 0}, "text": "@Newsweek @gabygente me encant\u00f3!", "created_at": "2015-06-27T02:28:53.000Z", "id": "614621393154650112", "referenced_tweets": [{"type": "replied_to", "id": "614618682543616000"}], "reply_settings": "everyone", "lang": "es", "author_id": "65618664", "entities": {"mentions": [{"start": 0, "end": 9, "username": "Newsweek", "id": "2884771"}]}, "in_reply_to_user_id": "2884771", "source": "Twitter for iPad"}