{"entities": {"mentions": [{"start": 0, "end": 16, "username": "reezustaughtyou", "id": "2498936086"}, {"start": 17, "end": 30, "username": "DirtyFlacko_", "id": "2741039206"}]}, "source": "Twitter for iPhone", "created_at": "2015-10-29T19:51:43.000Z", "text": "@ReezusTaughtYou @DirtyFlacko_ what in the fuck", "in_reply_to_user_id": "2498936086", "lang": "en", "public_metrics": {"retweet_count": 0, "reply_count": 0, "like_count": 0, "quote_count": 0}, "possibly_sensitive": false, "reply_settings": "everyone", "author_id": "768855415", "id": "659819922500005888", "referenced_tweets": [{"type": "replied_to", "id": "659819631146848256"}], "conversation_id": "659462980476637184"}